anel_power_control.py
setup.cfg
setup.py
AnelPowerControl.egg-info/PKG-INFO
AnelPowerControl.egg-info/SOURCES.txt
AnelPowerControl.egg-info/dependency_links.txt
AnelPowerControl.egg-info/not-zip-safe
AnelPowerControl.egg-info/requires.txt
AnelPowerControl.egg-info/top_level.txt