Metadata-Version: 1.1
Name: AnelPowerControl
Version: 0.1
Summary: Python library to control Anel Power Control Home/Pro.
Home-page: https://github.com/zdxerr/anel_power_control
Author: Christoph Schniedermeier
Author-email: UNKNOWN
License: UNKNOWN
Platform: any
Classifier: Environment :: Web Environment
Classifier: Intended Audience :: Developers
Classifier: Operating System :: OS Independent
Classifier: Programming Language :: Python
Classifier: Topic :: Software Development :: Libraries :: Python Modules
